[
  {
    "id": "_pb_users_auth_",
    "name": "users",
    "type": "auth",
    "system": false,
    "schema": [
      {
        "system": false,
        "id": "users_name",
        "name": "name",
        "type": "text",
        "required": false,
        "presentable": false,
        "unique": false,
        "options": {
          "min": null,
          "max": null,
          "pattern": ""
        }
      },
      {
        "system": false,
        "id": "users_avatar",
        "name": "avatar",
        "type": "file",
        "required": false,
        "presentable": false,
        "unique": false,
        "options": {
          "mimeTypes": ["image/jpeg", "image/png", "image/svg+xml", "image/gif", "image/webp"],
          "thumbs": null,
          "maxSelect": 1,
          "maxSize": 5242880,
          "protected": false
        }
      }
    ],
    "indexes": [],
    "listRule": "id = @request.auth.id",
    "viewRule": "id = @request.auth.id",
    "createRule": "",
    "updateRule": "id = @request.auth.id",
    "deleteRule": "id = @request.auth.id",
    "options": {
      "allowEmailAuth": true,
      "allowOAuth2Auth": true,
      "allowUsernameAuth": true,
      "exceptEmailDomains": null,
      "manageRule": null,
      "minPasswordLength": 8,
      "onlyEmailDomains": null,
      "onlyVerified": false,
      "requireEmail": false
    }
  },
  {
    "id": "hxhwpc2u127f6wh",
    "name": "work_experiences",
    "type": "base",
    "system": false,
    "schema": [
      {
        "system": false,
        "id": "zxrm1rmh",
        "name": "company_name",
        "type": "text",
        "required": false,
        "presentable": false,
        "unique": false,
        "options": {
          "min": null,
          "max": null,
          "pattern": ""
        }
      },
      {
        "system": false,
        "id": "i830u5xc",
        "name": "location",
        "type": "text",
        "required": false,
        "presentable": false,
        "unique": false,
        "options": {
          "min": null,
          "max": null,
          "pattern": ""
        }
      },
      {
        "system": false,
        "id": "317dgzw2",
        "name": "role",
        "type": "text",
        "required": false,
        "presentable": false,
        "unique": false,
        "options": {
          "min": null,
          "max": null,
          "pattern": ""
        }
      },
      {
        "system": false,
        "id": "aiz01wwz",
        "name": "description",
        "type": "editor",
        "required": false,
        "presentable": false,
        "unique": false,
        "options": {
          "convertUrls": false
        }
      },
      {
        "system": false,
        "id": "fsavyczi",
        "name": "started_at",
        "type": "date",
        "required": true,
        "presentable": false,
        "unique": false,
        "options": {
          "min": "",
          "max": ""
        }
      },
      {
        "system": false,
        "id": "3zo9lvae",
        "name": "ended_at",
        "type": "date",
        "required": false,
        "presentable": false,
        "unique": false,
        "options": {
          "min": "",
          "max": ""
        }
      },
      {
        "system": false,
        "id": "tx0ac8dd",
        "name": "type",
        "type": "select",
        "required": false,
        "presentable": false,
        "unique": false,
        "options": {
          "maxSelect": 1,
          "values": ["remote", "hybrid", "in-office"]
        }
      }
    ],
    "indexes": [],
    "listRule": null,
    "viewRule": null,
    "createRule": null,
    "updateRule": null,
    "deleteRule": null,
    "options": {}
  },
  {
    "id": "cdjipt7fqgyypk8",
    "name": "skills",
    "type": "base",
    "system": false,
    "schema": [
      {
        "system": false,
        "id": "c3fdqoer",
        "name": "name",
        "type": "text",
        "required": true,
        "presentable": false,
        "unique": false,
        "options": {
          "min": null,
          "max": null,
          "pattern": ""
        }
      }
    ],
    "indexes": [],
    "listRule": null,
    "viewRule": null,
    "createRule": null,
    "updateRule": null,
    "deleteRule": null,
    "options": {}
  },
  {
    "id": "lddf87uk6pf3qoh",
    "name": "projects",
    "type": "base",
    "system": false,
    "schema": [
      {
        "system": false,
        "id": "xmksrr8i",
        "name": "image",
        "type": "file",
        "required": false,
        "presentable": false,
        "unique": false,
        "options": {
          "mimeTypes": [],
          "thumbs": [],
          "maxSelect": 1,
          "maxSize": 5242880,
          "protected": false
        }
      },
      {
        "system": false,
        "id": "dokdu2dd",
        "name": "title",
        "type": "text",
        "required": true,
        "presentable": true,
        "unique": false,
        "options": {
          "min": null,
          "max": null,
          "pattern": ""
        }
      },
      {
        "system": false,
        "id": "3rouxsii",
        "name": "description",
        "type": "editor",
        "required": true,
        "presentable": false,
        "unique": false,
        "options": {
          "convertUrls": false
        }
      },
      {
        "system": false,
        "id": "hkw9dkxi",
        "name": "status",
        "type": "select",
        "required": true,
        "presentable": false,
        "unique": false,
        "options": {
          "maxSelect": 1,
          "values": ["in_progress", "completed"]
        }
      },
      {
        "system": false,
        "id": "4toawgt7",
        "name": "is_draft",
        "type": "bool",
        "required": false,
        "presentable": false,
        "unique": false,
        "options": {}
      },
      {
        "system": false,
        "id": "vcrphjyk",
        "name": "skills",
        "type": "relation",
        "required": false,
        "presentable": false,
        "unique": false,
        "options": {
          "collectionId": "cdjipt7fqgyypk8",
          "cascadeDelete": false,
          "minSelect": null,
          "maxSelect": 1,
          "displayFields": null
        }
      }
    ],
    "indexes": [],
    "listRule": null,
    "viewRule": null,
    "createRule": null,
    "updateRule": null,
    "deleteRule": null,
    "options": {}
  }
]
